Metadata-Version: 1.0
Name: kopo4group4
Version: 0.1.0
Summary: isoweek calculation and so on
Home-page: UNKNOWN
Author: kimjingyu
Author-email: km1031kim@naver.com
License: MIT
Keywords: calendar,isoweek
Platform: UNKNOWN
